Workbook

Sheet الملخص
B2: الجرد الشامل — كل عمليات سحب المنتجات (حتى 2026-10-02)
B4: الكيان | C4: المنصة / النطاق | D4: عدد المنتجات | E4: أدنى سعر $ | F4: أعلى سعر $ | G4: المتوفر | H4: تاريخ السحب | I4: الحكم
B5: StackVault — الكتالوج الحي | C5: stackvault.shop (decohomz.com/sv-api) | D5: 282 | E5: 0 | F5: 138.32 | G5: 228 | H5: 2026-10-02 ~03:25 +03 | I5: الهدف الرئيسي — مكتمل: cb_ 229 · ps_ 20 · mr_ 32 · dummy 1
B6: StackVault — أرشيف ما قبل الهجرة (مع costPrice) | C6: stackvault.shop (29-30/09) | D6: 357 | E6: 0 | F6: 138.32 | G6: 0 | H6: 2026-09-30 | I6: ذهب المفاوضات: تسريب costPrice مغلَق حاليًا — هامش الربح محسوب لكل منتج
B7: ProdSeller — منصة اللوحة الجملية | C7: prodseller.com (SookBit, OVH Strasbourg) | D7: 26 | E7: 0.09 | F7: 10 | G7: 23 | H7: 2026-09-29 | I7: اللوحة الأم لخط ps_/cb_ — cb_ = حساب جملة مباشر عليها (G-1 RESOLVED)
B8: PremiKey/HitMeow — canboso.com | C8: canboso.com/api/v2/telegram-buyer (tgb_ · X-API-Key · Binance Pay) | D8: 349 | E8: 0.04 | F8: 609.26 | G8: 249 | H8: 2026-10-02 ~04:15 +03 | I8: لوحة شقيقة من الحوض الكتالوجي المشترك (550 اسمًا) — قاعدة Mongo مستقلة؛ وسيط cb_/canboso = 0.91
B9: LahaStore — ver_pixel | C9: lahastore.up.railway.app/api/v1 (psk_) | D9: 15 | E9: 0.13 | F9: 115.63 | G9: 9 | H9: 2026-10-02 ~03:45 +03 | I9: مستبعد كمورد cb_ (صفر تطابق) — الأسعار بالدونج الفيتنامي محوّلة للدولار
B10: AIVerseX — aiversehub.store | C10: aiversehub.store/api/v1 (AK_) | D10: 35 | E10: 0.29 | F10: 80 | G10: 16 | H10: 2026-10-02 ~03:45 +03 | I10: مستبعد كمورد cb_ (صفر تطابق من 35 منتجًا)
B11: Gemini_Shop — واجهة aivaulthub | C11: reseller.aivaulthub.store/api/v1 (rsk_) | D11: 6 | E11: 0.35 | F11: 10 | G11: 5 | H11: 2026-10-02 ~03:45 +03 | I11: مستبعد (6 منتجات، صفر تطابق)
B12: Acczone — Mike_E_0 | C12: بوت تيليجرام (مفتاح مقتطع) | D12: 4 | E12: 0.3 | F12: 0.69 | G12: 4 | H12: 2026-10-02 ~03:45 +03 | I12: مستبعد (4 منتجات، صفر تطابق) — الكتالوج مصغّر
B13: DigitalCore — DCoreStoreBot | C13: digitalcore.top/api/user (UUID Api-Key) | D13: 11 | E13: 0.25 | F13: 13 | G13: 10 | H13: 2026-10-02 ~04:15 +03 | I13: مورد جملة API موثق (تدرجات كمية +12-47%) — مستبعد كهوية cb_
B14: AIXpress — aixpress.shop | C14: aixpress.shop/api/v1 (AK_ — نشر فعلي؛ وثائق البوت متقادمة) | D14: 2 | E14: 0.45 | F14: 0.65 | G14: 0 | H14: 2026-10-02 ~04:19 +03 | I14: خامِل: منتجان فقط، مخزون 0، رصيد $0 — نفس صندوق AIVerseX (188.166.90.19)
B15: RichAIStore — cgpt-active.pro | C15: cgpt-active.pro/telegram/api/v1 (Bearer rsk_ · Reseller API v1.0.0) | D15: 25 | E15: 0.6 | F15: 40 | G15: 15 | H15: 2026-10-02 ~04:19 +03 | I15: منصة CDK كاملة التوثيق (12 نقطة نهاية + تذاكر) — مستبعدة (صفر تطابق مع cb_)
B16: بوابة teamsoclo (نماذج API) | C16: gpt.teamsoclo.site/api/pricing (Team Sóc Lọ 🇻🇳) | D16: 15 | H16: 2026-10-02 02:49 +03 | I16: بوابة الجملة العليا المترابطة مع cb_ (Team Sóc Lọ)
B17: الإجمالي — سجلات المنتجات (11 كتالوجًا) | D17: 1112
B19: المصدر الموحد: research/sv_master_catalog_consolidated_20261002.json · الإصدار المرجعي: PMRF v1.4
B20: LahaStore prices in VND converted at 25945 VND/USD (canboso usdRate, 2026-10-02)
B21: أرشيف StackVault يتضمن costPrice المسرب (أُغلق لاحقًا) — الهوامش: وسيط +20.1% · نطاق +15% إلى +154.3%
B22: المستبعد كهوية cb_ (صفر تطابق): laha · aivx · gshop · acczone · dcore · aixpress · richai · canboso (قاعدة منفصلة)
B23: المتبقي المفتوح: G-7 شراء اختباري (الهوية القانونية لمشغّل cb_) — كل مفاتيح Ahmed تعمل لحساب TG 7334478984

Sheet StackVault_الحي
B2: StackVault — الكتالوج الحي (282 منتجًا · سحب 2026-10-02)
B4: المعرف | C4: المنتج | D4: الفئة | E4: البادئة | F4: السعر $ | G4: المخزون | H4: متوفر | I4: مقتطف الوصف
B5: dummy-free-test | C5: Free Test Key | D5: Digital Services | E5: other | F5: 0 | G5: 999 | H5: نعم | I5: A free dummy product to test the purchasing flow without spending balance.
B6: cb_6abb2c37a3c899e94310692c | C6: 🎨 ChatGPT Go 1 Month (10-Day Warranty) | D6: ChatGPT | E6: cb | F6: 3.66 | G6: 20 | H6: نعم | I6: Format: Email|Password|2FA 📌 Instructions to get 2FA OTP 1️⃣ Visit website: 2FA.LIVE 2️⃣ Copy the 2FA Secret provided in the product file. 3…
B7: cb_6abdef24da57cd63e0e4b8af | C7: 🎨 ChatGPT Plus 1 Month 3D warranty | D7: ChatGPT | E7: cb | F7: 8.79 | G7: 2 | H7: نعم | I7: 🔐 Private account — can freely change Password & 2FA 📂 Format: Email | Password | 2FA ✅ 30-day warranty for lost package or downgraded packa…
B8: cb_6abb80a5dcfd14a98e56ef16 | C8: 🎨 ChatGPT Plus 1 Month full warranty | D8: ChatGPT | E8: cb | F8: 12.02 | G8: 15 | H8: نعم | I8: 🔐 Private account — can freely change Password & 2FA 📂 Format: Email | Password | 2FA ✅ 30-day warranty for lost package or downgraded packa…
B9: cb_6abd0ed27e196463ea3a567f | C9: 🎨 ChatGPT Plus 1 Month full warranty | D9: ChatGPT | E9: cb | F9: 11.79 | G9: 0 | H9: لا | I9: 🔐 Private account — can freely change Pass & 2FA 📂 Format: Email | Pass | 2FA ✅ 30-day warranty for lost package or downgrade ⚠️ NOTE: 1. Co…
B10: cb_6ab9042f266735c89776a297 | C10: 🤖 ChatGPT Plus 30 Days (GGPay) | D10: ChatGPT | E10: cb | F10: 8.32 | G10: 0 | H10: لا | I10: 🔐 Private account — can freely change Pass & 2FA 📂 Format: Email | Pass | 2FA ✅ Account has been checked for Pass & 2FA before selling. ⚠️ N…
B11: cb_6ab0a59af6d40479fdc3fe64 | C11: 🎨 ChatGPT PRO X5 1 month - 7 Days warranty | D11: ChatGPT | E11: cb | F11: 78.53 | G11: 4 | H11: نعم | I11: - Ordered items, return orders within 48H - Pay INAPP items super strong
B12: cb_6ab7d2db0f9ff38abc2fc24d | C12: 🎨 ChatGPT Ver Students Plus 4 Months without warranty | D12: ChatGPT | E12: cb | F12: 16.16 | G12: 2 | H12: نعم | I12: 🎓 Pre-verified STUDENT account — Not paid 🔗 Check at: https://chatgpt.com/students/2026 ⚠️ No warranty for payment. Check done = no warranty…
B13: cb_6ab7ed4378e9610e9e36d783 | C13: GPT Plus Level 4, 24H warranty | D13: ChatGPT | E13: cb | F13: 23.09 | G13: 0 | H13: لا | I13: 🔐 Private account — can freely change Pass & 2FA 📂 Format: Email | Pass | 2FA ✅ Account has been checked for Pass & 2FA before selling. ⚠️ N…
B14: cb_6ab9647a266735c89784e6b4 | C14: 🎨 Shared ChatGPT account with a full 1-month warranty | D14: ChatGPT | E14: cb | F14: 5.49 | G14: 15 | H14: نعم | I14: ✅ This is a business SLOT account, renewable monthly 👥 Pre-assigned account — 1 account/1 device / 3 users 🛡️ Only package warranty, no warr…
B15: cb_6abc82ed17aa4c8f035618c1 | C15: 🎨 Slot GPT Business can be extended by 1 month with full warranty | D15: ChatGPT | E15: cb | F15: 19.82 | G15: 0 | H15: لا | I15: Can be extended! Warranty conditions • The Seat can only be used for legal purposes and must fully comply with OpenAI's policies and regulat…
B16: cb_6ab3f5f90944def028bf1fe7 | C16: 🤖 1B Credit API Codex 14 Days - full warranty | D16: API Codex | E16: cb | F16: 41.44 | G16: 44 | H16: نعم | I16: Base URL: https://gpt.teamsoclo.site/v1 Model: gpt-5.6-sol, gpt-6-sol, gpt-6.1-sol, gpt-6-luna User Manual: https://docs.teamsoclo.site/ Vid…
... B286: mr_warp-build | C286: Warp Build 12m | D286: Other Products | E286: mr | F286: 12 | G286: 1 | H286: نعم | I286: ⚡ Duration: 12 Month ⚡ Official Coupon Code 🚫 No Warranty After Coupon Activation ⚡ On Your Account ⚠️ Please note that the code must be red…

Sheet StackVault_الأرشيف
B2: StackVault — أرشيف ما قبل الهجرة (357 منتجًا مع costPrice · 29-30/09)
B4: المعرف | C4: المنتج | D4: الفئة | E4: البادئة | F4: التكلفة $ (مسربة) | G4: السعر $ | H4: هامش الربح % | I4: المخزون
B5: dummy-free-test | C5: Free Test Key | D5: Digital Services | E5: other | F5: 0 | G5: 0 | H5: =IF(OR(F5="",F5=0),"",(G5-F5)/F5) | I5: 999
B6: ps_6aacdb525271203cb12d8603 | C6: ✅🌐 (can be monetized) Upgrade X Premium 3 months full warranty | D6: Digital Services | E6: ps | F6: 9.53 | G6: 11.44 | H6: =IF(OR(F6="",F6=0),"",(G6-F6)/F6) -> 0.20041973 | I6: 95
B7: ps_6aacdb585271203cb12d874c | C7: ✅🌐 (can be monetized) Upgrade X Premium 6 months full warranty | D7: Digital Services | E7: ps | F7: 13.33 | G7: 16 | H7: =IF(OR(F7="",F7=0),"",(G7-F7)/F7) -> 0.20030008 | I7: 57
B8: ps_6ab4b86471af64b485ebe66c | C8: (💚So Beautiful) Chatgpt Plus Apple Pay 1 month full warranty | D8: AI Subscriptions | E8: ps | F8: 10.67 | G8: 12.81 | H8: =IF(OR(F8="",F8=0),"",(G8-F8)/F8) -> 0.20056232 | I8: 0
B9: ps_6aacd09c5271203cb12b5525 | C9: 🤖 1B Credit API Codex 2 Days - full warranty | D9: Design & Editing | E9: ps | F9: 19.21 | G9: 23.06 | H9: =IF(OR(F9="",F9=0),"",(G9-F9)/F9) -> 0.20041645 | I9: 28
B10: ps_6aaccf715271203cb12b2504 | C10: 🤖 100M Credit API Codex 1 Day - full warranty | D10: Design & Editing | E10: ps | F10: 3.05 | G10: 3.66 | H10: =IF(OR(F10="",F10=0),"",(G10-F10)/F10) -> 0.2 | I10: 72
B11: ps_6aaccf7f5271203cb12b2724 | C11: 🤖 100M Credit API Codex 5 Days - full warranty | D11: Design & Editing | E11: ps | F11: 3.81 | G11: 4.58 | H11: =IF(OR(F11="",F11=0),"",(G11-F11)/F11) -> 0.20209974 | I11: 40
B12: ps_6aaed84c86b424201498de26 | C12: 💰 105K Decor Discord / Profile Effect Cheap (Login Type) - full warranty | D12: Digital Services | E12: ps | F12: 4.19 | G12: 5.03 | H12: =IF(OR(F12="",F12=0),"",(G12-F12)/F12) -> 0.20047733 | I12: 182
B13: ps_6aaccf2e5271203cb12b18d2 | C13: 🤖 10M Credit API Codex 1 Day - full warranty | D13: Design & Editing | E13: ps | F13: 0.96 | G13: 1.23 | H13: =IF(OR(F13="",F13=0),"",(G13-F13)/F13) -> 0.28125 | I13: 145
B14: ps_6aafeff086b4242014b9880a | C14: 🤖 10M Credit API Codex 2 Days - full warranty | D14: Design & Editing | E14: ps | F14: 1.53 | G14: 1.96 | H14: =IF(OR(F14="",F14=0),"",(G14-F14)/F14) -> 0.28104575 | I14: 80
B15: ps_6aaed84586b424201498dd20 | C15: 💰 111K Decor Discord / Profile Effect Cheap (Login Type) - full warranty | D15: Digital Services | E15: ps | F15: 4.57 | G15: 5.49 | H15: =IF(OR(F15="",F15=0),"",(G15-F15)/F15) -> 0.20131291 | I15: 173
B16: ps_6aaed83986b424201498dc5e | C16: 💰 131K Decor Discord / Profile Effect Cheap (Login Type) - full warranty | D16: Digital Services | E16: ps | F16: 5.72 | G16: 6.87 | H16: =IF(OR(F16="",F16=0),"",(G16-F16)/F16) -> 0.20104895 | I16: 144
... B361: ps_6aacd8295271203cb12ce9f3 | C361: 🔥Minimax Redeem 3M Credit | D361: Design & Editing | E361: ps | F361: 26.62 | G361: 31.95 | H361: =IF(OR(F361="",F361=0),"",(G361-F361)/F361) -> 0.20022539 | I361: 26

Sheet الكيانات_الخارجية
B2: الكيانات الخارجية — الكتالوجات المسحوبة بالمفاتيح (473 سجلًا · 9 كيانات)
B4: الكيان | C4: المعرف | D4: المنتج | E4: النوع/الفئة | F4: السعر $ | G4: المخزون | H4: متوفر | I4: ملاحظة
B5: ProdSeller | C5: 6a612473af18a2a83bc049a0 | D5: Gmails Accounts | F5: 0.6 | H5: نعم | I5: publicPrice: $0.65 · بيع: 798
B6: ProdSeller | C6: 6a6207cf92969197bb382958 | D6: iLovePdf Premium 1Yr | F6: 0.45 | H6: نعم | I6: publicPrice: $0.49 · بيع: 665
B7: ProdSeller | C7: 6a5b873847b606c66fc160b2 | D7: Adobe Express 12M | F7: 0.35 | H7: نعم | I7: publicPrice: $0.39 · بيع: 752
B8: ProdSeller | C8: 6a2fda51035a6d898f2106fe | D8: Capcut Pro 1 Month FW | F8: 1.25 | H8: نعم | I8: publicPrice: $1.29 · بيع: 18548
B9: ProdSeller | C9: 6a2fe23a1c8697b163aedcbd | D9: Microsoft Office 365 Plus 1 year | F9: 0.21 | H9: نعم | I9: publicPrice: $0.29 · بيع: 5261
B10: ProdSeller | C10: 6a2fdb4f035a6d898f2106ff | D10: Canva Pro Admin (500 invitations) | F10: 2.5 | H10: نعم | I10: publicPrice: $2.9 · بيع: 266
B11: ProdSeller | C11: 6a31035939dc014325da2c66 | D11: Gemini Pro 18Months (link) | F11: 0.6 | H11: نعم | I11: publicPrice: $0.65 · بيع: 223803
B12: ProdSeller | C12: 6a316a7b1777fc2347835653 | D12: Canva Pro 2 yrs FW | F12: 0.6 | H12: نعم | I12: publicPrice: $0.6 · بيع: 912
B13: ProdSeller | C13: 6a3d636221735658e32bd2a6 | D13: Prime Video 6 Months | F13: 1.5 | H13: نعم | I13: publicPrice: $1.7 · بيع: 253
B14: ProdSeller | C14: 6a54b931351561c645a43e8c | D14: Notion Plus 12M | F14: 1.1 | H14: نعم | I14: publicPrice: $1.3 · بيع: 475
B15: ProdSeller | C15: 6a4bf6b502999800df9660b1 | D15: Capcut Pro 7D FW | F15: 0.13 | H15: نعم | I15: publicPrice: $0.14 · بيع: 3220
B16: ProdSeller | C16: 6a495a5f02999800df961920 | D16: ChatGPT Plus K12 Edu 2 years | F16: 3.4 | H16: لا | I16: publicPrice: $3.5 · بيع: 1568
... B30: ProdSeller | C30: 6abeb3210dbb401865ffe95f | D30: Wispr Flow 12M Edu | F30: 5.6 | H30: نعم | I30: publicPrice: $6.0 · بيع: 0
B31: LahaStore | C31: 15 | D31: ChatGPT Plus 1 Month GGPay - Warranty 1 Day | E31: ChatGPT | F31: 6.94 | G31: 0 | H31: لا | I31: الأصلي: 180,000 VND
B32: LahaStore | C32: 20 | D32: ChatGPT Pre-registered account using @gmail ( free not plus ) | E32: ChatGPT | F32: 0.13 | G32: 0 | H32: لا | I32: الأصلي: 3,500 VND
B33: LahaStore | C33: 23 | D33: ChatGPT Plus 1 Month UPI @gmail- Warranty 5h | E33: ChatGPT | F33: 4.63 | G33: 19 | H33: نعم | I33: الأصلي: 120,000 VND
B34: LahaStore | C34: 36 | D34: API 10M Token Codex 1 Day - Full Warranty | E34: ChatGPT | F34: 1.77 | G34: 0 | H34: لا | I34: الأصلي: 46,000 VND
B35: LahaStore | C35: 37 | D35: API 50M Token Codex 1 Day - Full Warranty | E35: ChatGPT | F35: 2.7 | G35: 14 | H35: نعم | I35: الأصلي: 70,000 VND
B36: LahaStore | C36: 38 | D36: API 100M Token Codex 1 Day - Full Warranty | E36: ChatGPT | F36: 3.47 | G36: 13 | H36: نعم | I36: الأصلي: 90,000 VND
B37: LahaStore | C37: 14 | D37: Gemini Pro — 18 Months (Links) | E37: Gemini AI | F37: 1 | G37: 33 | H37: نعم | I37: الأصلي: 26,000 VND
B38: LahaStore | C38: 66 | D38: Tool Jio Gemini Pro Extractor, Check Link, Scan Panel | E38: Gemini AI | F38: 115.63 | G38: 1 | H38: نعم | I38: الأصلي: 3,000,000 VND
B39: LahaStore | C39: 21 | D39: CAPCUT PRO 30D - Full Warranty | E39: Capcut | F39: 2.12 | G39: preorder | H39: لا | I39: الأصلي: 55,000 VND
B40: LahaStore | C40: 70 | D40: Capcut 6 Month - Full Warranty | E40: Capcut | F40: 10.02 | G40: preorder | H40: لا | I40: الأصلي: 260,000 VND
B41: LahaStore | C41: 32 | D41: API 10M Token Claude 1 Day - Full Warranty | E41: Claude | F41: 1.77 | G41: 15 | H41: نعم | I41: الأصلي: 46,000 VND
B42: LahaStore | C42: 33 | D42: API 50M Token Claude 1 Day - Full Warranty | E42: Claude | F42: 3.82 | G42: 15 | H42: نعم | I42: الأصلي: 99,000 VND
B43: LahaStore | C43: 34 | D43: API 100M Token Claude 1 Day - Full Warranty | E43: Claude | F43: 5.2 | G43: 35 | H43: نعم | I43: الأصلي: 135,000 VND
B44: LahaStore | C44: 28 | D44: Dropshot AI 600 Credits (W12H) | E44: Dropshot AI | F44: 0.69 | G44: 4 | H44: نعم | I44: الأصلي: 18,000 VND
B45: LahaStore | C45: 74 | D45: Duolingo Super 12 Month | E45: Duolingo | F45: 0.71 | G45: preorder | H45: لا | I45: الأصلي: 18,500 VND
B46: AIVerseX | C46: service_1786031496 | D46: Netflix 1M Premium 4K HDR | F46: 2.5 | G46: 0 | H46: لا
B47: AIVerseX | C47: service_1787461848 | D47: Spotify 3M Redeem Link | F47: 0.35 | G47: 0 | H47: لا
B48: AIVerseX | C48: service_1788995417 | D48: Duolingo Super 12M | F48: 0.4 | G48: 0 | H48: لا
B49: AIVerseX | C49: service_1788995793 | D49: Adobe Express 12M | F49: 0.4 | G49: 180 | H49: نعم
B50: AIVerseX | C50: service_1788996027 | D50: Apple Music 5M | F50: 0.85 | G50: 207 | H50: نعم
B51: AIVerseX | C51: service_1789408882 | D51: Cursor Pro 12M | F51: 70 | G51: 0 | H51: لا
B52: AIVerseX | C52: service_1789409173 | D52: ElevenLabs Creator 12M | F52: 35 | G52: 0 | H52: لا
B53: AIVerseX | C53: service_1789409348 | D53: Factory 12M | F53: 15 | G53: 1 | H53: نعم
B54: AIVerseX | C54: service_1789409519 | D54: Framer Pro 12M | F54: 10 | G54: 3 | H54: نعم
B55: AIVerseX | C55: service_1789409622 | D55: Gamma Pro 12M | F55: 20 | G55: 1 | H55: نعم
B56: AIVerseX | C56: service_1789409720 | D56: Google AI Pro 12M | F56: 13 | G56: 0 | H56: لا
B57: AIVerseX | C57: service_1789409889 | D57: Granola Business | F57: 3 | G57: 1 | H57: نعم
... B86: Gemini_Shop | C86: service_1790855554 | D86: ChatGPT Plus UPI (24H) | F86: 5 | G86: 10 | H86: نعم
B87: Acczone | C87: ADOBE_EXPRESS | D87: Adobe Express 12M | F87: 0.3 | H87: نعم
B88: Acczone | C88: APPLE_MUSIC_PREPAID_V2 | D88: Apple Music 5M | F88: 0.3 | H88: نعم
B89: Acczone | C89: DUOLINGO | D89: Duolingo Super 12M | F89: 0.35 | H89: نعم
B90: Acczone | C90: geminilive | D90: Gemini Pro 18M NEW | F90: 0.69 | H90: نعم
B91: PremiKey/HitMeow | C91: 6aab67b4ccf9b248c4b395b6 | D91: ChatGPT Gmail Trial offers 1 month Apple Pay - no warranty | E91: account | F91: 1.87 | G91: 0 | H91: لا | I91: بيعت: 13803
B92: PremiKey/HitMeow | C92: 6aa97801cac93afd8876ce3e | D92: CHATGPT PLUS 30 DAYS (no warranty) | E92: account | F92: 7.21 | G92: 1 | H92: نعم | I92: بيعت: 395
B93: PremiKey/HitMeow | C93: 6abe2315da57cd63e0eec464 | D93: ChatGPT Plus 1 Month (No warranty) | E93: account | F93: 5.56 | G93: 11 | H93: نعم | I93: بيعت: 469
B94: PremiKey/HitMeow | C94: 6abe22ccda57cd63e0eeb377 | D94: CHAT GPT PLUS 1 MONTH WARRANTY 5H | E94: account | F94: 5.01 | G94: 7 | H94: نعم | I94: بيعت: 14
B95: PremiKey/HitMeow | C95: 6aaa7c80fbab5ba20a1a7006 | D95: ChatGPT Plus 30D warranty 24H | E95: account | F95: 7.61 | G95: 33 | H95: نعم | I95: بيعت: 1621
B96: PremiKey/HitMeow | C96: 6abcae227181c2d56304da99 | D96: GPT GO 1 MONTH (24H warranty) | E96: account | F96: 3.77 | G96: 7 | H96: نعم | I96: بيعت: 14
B97: PremiKey/HitMeow | C97: 6aa39f0b0de12c6992d9d6c9 | D97: ChatGPT Business Slot 1 month warranty 24h | E97: slot | F97: 12.82 | G97: 40 | H97: نعم | I97: بيعت: 0
B98: PremiKey/HitMeow | C98: 6ab57013675d4138eb96c7c7 | D98: ChatGPT PRO 5X 1 month - 3D warranty | E98: account | F98: 76.13 | G98: 0 | H98: لا | I98: بيعت: 18
B99: PremiKey/HitMeow | C99: 6ab5701e675d4138eb96c85b | D99: CHAT GPT PRO X5 1 MONTH (5-DAY WARRANTY) | E99: account | F99: 79.94 | G99: 0 | H99: لا | I99: بيعت: 14
B100: PremiKey/HitMeow | C100: 6abaa96aa3c899e943fd7149 | D100: 🔥ChatGPT Plus VIP Pro 30D warranty 20D | E100: account | F100: 9.87 | G100: 12 | H100: نعم | I100: بيعت: 33
B101: PremiKey/HitMeow | C101: 6aba27a431a482e3ae1d4f07 | D101: ❤️‍🔥 Slot ChatGPT Business can be extended for 30 days with full warranty | E101: slot | F101: 17.48 | G101: 26 | H101: نعم | I101: بيعت: 231
B102: PremiKey/HitMeow | C102: 6abe195cda57cd63e0ecc9ee | D102: 💚ChatGPT Plus Apple Pay 1 month full warranty | E102: account | F102: 11.39 | G102: 16 | H102: نعم | I102: بيعت: 2534
... B115: PremiKey/HitMeow | C115: 6a6e1eb44e24e64b8f018278 | D115: 🔥ElevenLabs Redeem 7M Credit | E115: account | F115: 53.77 | G115: 121 | H115: نعم | I115: بيعت: 80
B116: PremiKey/HitMeow | C116: 6aa2ee48553547f0f1083e6f | D116: 🔥ElevenLabs Redeem Creator 12 months | E116: upgrade_account | F116: 49.89 | H116: لا | I116: بيعت: 1
B117: PremiKey/HitMeow | C117: 6aa6d8b0130136d7700328cd | D117: Link Gift EleveneReadr Ultra 1 year warranty 1 day | E117: account | F117: 3.77 | G117: 4 | H117: نعم | I117: بيعت: 211
B118: PremiKey/HitMeow | C118: 6a9d73ceeab261fc8b661bdb | D118: 🔥ElevenLabs Redeem 131K Credit | E118: account | F118: 1.85 | G118: 373 | H118: نعم | I118: بيعت: 377
B119: PremiKey/HitMeow | C119: 6a721f4db6d374ae89ca4172 | D119: 🔥ElevenLabs Redeem 300K Credit | E119: account | F119: 4.6 | G119: 554 | H119: نعم | I119: بيعت: 1637
B120: PremiKey/HitMeow | C120: 6abe8fe98e14fb435f2c5058 | D120: Capcut Pro 7 Days full warranty | E120: account | F120: 0.42 | G120: 18 | H120: نعم | I120: بيعت: 652
B121: PremiKey/HitMeow | C121: 6ab57e75675d4138eb9831f3 | D121: Capcut Pro 30D with a 30-day warranty | E121: account | F121: 1.85 | G121: 9 | H121: نعم | I121: بيعت: 201
B122: PremiKey/HitMeow | C122: 6a8762c7cb69f3270dc04b80 | D122: CapCut Pro Team 3 Months - full warranty | E122: account | F122: 6.94 | G122: 7 | H122: نعم | I122: بيعت: 248
B123: PremiKey/HitMeow | C123: 6ab7a3850f9ff38abc2828e6 | D123: CAPCUT PERSONAL 6 MONTHS full warranty | E123: account | F123: 10.25 | G123: 10 | H123: نعم | I123: بيعت: 220
B124: PremiKey/HitMeow | C124: 6aaeeefe86b42420149b76fa | D124: Claude Unlimited API 1-day full warranty | E124: account | F124: 11.49 | G124: 2 | H124: نعم | I124: بيعت: 4
B125: PremiKey/HitMeow | C125: 6abbe15817aa4c8f033f7358 | D125: VIP API Claude Unlimited 1 day full warranty | E125: account | F125: 19.17 | G125: 0 | H125: لا | I125: بيعت: 2
B126: PremiKey/HitMeow | C126: 6ab3eef60944def028bdd5c5 | D126: Claude API $10 1 month full warranty | E126: account | F126: 0.97 | G126: 95 | H126: نعم | I126: بيعت: 125
B127: PremiKey/HitMeow | C127: 6ab3ef380944def028bde2f7 | D127: Claude API $30 1 month full warranty | E127: account | F127: 1.89 | G127: 71 | H127: نعم | I127: بيعت: 39
B128: PremiKey/HitMeow | C128: 6ab3efe00944def028be02f7 | D128: Claude API $50 1 month full warranty | E128: account | F128: 3.04 | G128: 46 | H128: نعم | I128: بيعت: 34
... B152: PremiKey/HitMeow | C152: 6ab36ae60944def028a751c5 | D152: CHEAP YOUTUBE PREMIUM SLOT 12 MONTHS full warranty | E152: slot | F152: 10.06 | G152: 1 | H152: نعم | I152: بيعت: 0
B153: PremiKey/HitMeow | C153: 6aab93dbbb8cc3ed24a4cd2d | D153: Buff 1M followers YouTube channel 1 year no warranty | E153: upgrade_account | F153: 38.73 | H153: لا | I153: بيعت: 0
B154: PremiKey/HitMeow | C154: 6aab92dcbb8cc3ed24a4a91f | D154: Buff 10k followers YouTube channel 1 year no warranty | E154: upgrade_account | F154: 1.13 | H154: لا | I154: بيعت: 0
B155: PremiKey/HitMeow | C155: 6aab93a6bb8cc3ed24a4c4be | D155: Buff 100k followers YouTube channel 1 year no warranty | E155: upgrade_account | F155: 7.37 | H155: لا | I155: بيعت: 0
B156: PremiKey/HitMeow | C156: 6aa962cfce0dc91737d842a1 | D156: Co Viet YouTube Channel 201X-2025 | E156: account | F156: 3.39 | G156: 0 | H156: لا | I156: بيعت: 297
B157: PremiKey/HitMeow | C157: 6aaabbcb22a653bc6d020638 | D157: Vietnam 2026 YouTube Channel - Old Gmail | E157: account | F157: 2.25 | G157: 0 | H157: لا | I157: بيعت: 48
B158: PremiKey/HitMeow | C158: 6a97f1895aadae258c3a36b6 | D158: Notion Business Admin 1 month full warranty | E158: account | F158: 5.68 | G158: 3 | H158: نعم | I158: بيعت: 92
B159: PremiKey/HitMeow | C159: 6a9c4ea6d92ddad6f97f09df | D159: Slot Notion Business has an official AI with a full 1-month warranty | E159: slot | F159: 1.87 | G159: 15 | H159: نعم | I159: بيعت: 0
B160: PremiKey/HitMeow | C160: 6a8fc3ea661bc6770a23f417 | D160: Notion Business Admin 3 months full warranty | E160: account | F160: 19.01 | G160: 2 | H160: نعم | I160: بيعت: 162
B161: PremiKey/HitMeow | C161: 6a97f1915aadae258c3a379c | D161: Notion Business Code 3 months full warranty | E161: account | F161: 8.73 | G161: 10 | H161: نعم | I161: بيعت: 63
B162: PremiKey/HitMeow | C162: 6a9c4eb0d92ddad6f97f0ba3 | D162: Slot Notion Business has an official AI with a full 3-month warranty | E162: slot | F162: 3.39 | G162: 14 | H162: نعم | I162: بيعت: 1
B163: PremiKey/HitMeow | C163: 6aa2f062553547f0f10871ca | D163: Notion Business Redeem 1 year | E163: upgrade_account | F163: 19.31 | H163: لا | I163: بيعت: 0
B164: PremiKey/HitMeow | C164: 6a74666836760d994b33dbe9 | D164: Notion Plus 1 year full warranty | E164: account | F164: 9.87 | G164: 10 | H164: نعم | I164: بيعت: 29
B165: PremiKey/HitMeow | C165: 6aa02c7d90645ea2198cf5d3 | D165: 🔥Notion plus edu 2 years warranty 3 months | E165: account | F165: 3.85 | G165: 2 | H165: نعم | I165: بيعت: 3
B166: PremiKey/HitMeow | C166: 6aaed31486b424201497ed6c | D166: Adobe All App 6-7 Days no warranty | E166: account | F166: 1.87 | G166: 0 | H166: لا | I166: بيعت: 172
B167: PremiKey/HitMeow | C167: 6aa4ed1cdf59fbc6fe0caeff | D167: Adobe All Apps 7 Days no warranty | E167: account | F167: 3.01 | G167: 4 | H167: نعم | I167: بيعت: 1377
B168: PremiKey/HitMeow | C168: 6ab911a6266735c897788c0f | D168: Adobe All Apps 7D warranty 12H | E168: account | F168: 3.39 | G168: 4 | H168: نعم | I168: بيعت: 592
B169: PremiKey/HitMeow | C169: 6aa93413910baa7b964052d3 | D169: Adobe Full App Bypass Version 1 Month - full warranty | E169: account | F169: 3.77 | G169: 2 | H169: نعم | I169: بيعت: 47
B170: PremiKey/HitMeow | C170: 6abd4cbc7e196463ea475fd8 | D170: Adobe Express Premium 12 months no warranty | E170: account | F170: 1.87 | G170: 5 | H170: نعم | I170: بيعت: 45
B171: PremiKey/HitMeow | C171: 6aa58f89df59fbc6fe22d163 | D171: Adobe Express Premium 12 months without warranty | E171: account | F171: 2.25 | G171: 12 | H171: نعم | I171: بيعت: 9
B172: PremiKey/HitMeow | C172: 6a9a130402debacfb80da062 | D172: Figma Pro Education 2 Years warranty 1 Year | E172: account | F172: 7.58 | G172: 6 | H172: نعم | I172: بيعت: 89
B173: PremiKey/HitMeow | C173: 6ab017cb86b4242014c10d69 | D173: KLING 700-900 per month (24h warranty) | E173: account | F173: 7.58 | G173: 0 | H173: لا | I173: بيعت: 225
B174: PremiKey/HitMeow | C174: 6ab017b386b4242014c10997 | D174: Kling Standard 660-690 credit 1 month warranty 1 day | E174: account | F174: 6.44 | G174: 0 | H174: لا | I174: بيعت: 9
B175: PremiKey/HitMeow | C175: 6ab58018675d4138eb985444 | D175: Kling Standard 726 credit 1 month warranty 1 day | E175: account | F175: 6.44 | G175: 0 | H175: لا | I175: بيعت: 12
... B230: PremiKey/HitMeow | C230: 6abbf04b17aa4c8f03429518 | D230: Lovable Lite 12 months - 2 months warranty | E230: account | F230: 9.87 | G230: 8 | H230: نعم | I230: بيعت: 5
B231: PremiKey/HitMeow | C231: 6a9fcd14b0f7cc50800d50f6 | D231: ⚡️Lovable Lite slot 1 year warranty 3 months | E231: slot | F231: 10.46 | H231: لا | I231: بيعت: 1
B232: PremiKey/HitMeow | C232: 6aa2f54a553547f0f108f766 | D232: Lovable Pro Redeem 1 year | E232: upgrade_account | F232: 53.75 | H232: لا | I232: بيعت: 1
...

Sheet مقارنة_الأسعار
B2: مقارنة الأسعار — cb_ مقابل canboso/PremiKey (111 زوجًا متطابقًا بالاسم)
B4: المنتج | C4: سعر cb_ $ | D4: سعر canboso $ | E4: النسبة cb_/canboso | F4: قراءة
B5: 💰 105K Decor Discord / Profile Effect Cheap (Login Type) - full warranty | C5: 5.03 | D5: 6.06 | E5: =IFERROR(C5/D5,"") -> 0.830033 | F5: =IF(E5="","",IF(E5<0.8,"cb_ أرخص بوضوح",IF(E5<=1.05,"تقارب","canboso أرخص"))) -> تقارب
B6: 💰 111K Decor Discord / Profile Effect Cheap (Login Type) - full warranty | C6: 5.49 | D6: 6.44 | E6: =IFERROR(C6/D6,"") -> 0.85248447 | F6: =IF(E6="","",IF(E6<0.8,"cb_ أرخص بوضوح",IF(E6<=1.05,"تقارب","canboso أرخص"))) -> تقارب
B7: 💰 131K Decor Discord / Profile Effect Cheap (Login Type) - full warranty | C7: 6.87 | D7: 6.82 | E7: =IFERROR(C7/D7,"") -> 1.0073314 | F7: =IF(E7="","",IF(E7<0.8,"cb_ أرخص بوضوح",IF(E7<=1.05,"تقارب","canboso أرخص"))) -> تقارب
B8: 💰 141K Decor Discord / Profile Effect Cheap (Login Type) - full warranty | C8: 8.24 | D8: 8.34 | E8: =IFERROR(C8/D8,"") -> 0.98800959 | F8: =IF(E8="","",IF(E8<0.8,"cb_ أرخص بوضوح",IF(E8<=1.05,"تقارب","canboso أرخص"))) -> تقارب
B9: 💰 170K Decor Discord / Profile Effect Cheap (Login Type) - full warranty | C9: 9.6 | D9: 9.11 | E9: =IFERROR(C9/D9,"") -> 1.053787 | F9: =IF(E9="","",IF(E9<0.8,"cb_ أرخص بوضوح",IF(E9<=1.05,"تقارب","canboso أرخص"))) -> canboso أرخص
B10: 💰 66K Decor Discord / Profile Effect Cheap (Login Type) - full warranty | C10: 2.98 | D10: 3.77 | E10: =IFERROR(C10/D10,"") -> 0.79045093 | F10: =IF(E10="","",IF(E10<0.8,"cb_ أرخص بوضوح",IF(E10<=1.05,"تقارب","canboso أرخص"))) -> cb_ أرخص بوضوح
B11: 💰 79K Decor Discord / Profile Effect Cheap (Login Type) - full warranty | C11: 3.44 | D11: 4.16 | E11: =IFERROR(C11/D11,"") -> 0.82692308 | F11: =IF(E11="","",IF(E11<0.8,"cb_ أرخص بوضوح",IF(E11<=1.05,"تقارب","canboso أرخص"))) -> تقارب
B12: 💰 92K Decor Discord / Profile Effect Cheap (Login Type) - full warranty | C12: 4.12 | D12: 4.92 | E12: =IFERROR(C12/D12,"") -> 0.83739837 | F12: =IF(E12="","",IF(E12<0.8,"cb_ أرخص بوضوح",IF(E12<=1.05,"تقارب","canboso أرخص"))) -> تقارب
B13: ✅🌐 Account X Stock 2009-2022 US Bull-Bear-BH24H | C13: 1.72 | D13: 2.25 | E13: =IFERROR(C13/D13,"") -> 0.76444444 | F13: =IF(E13="","",IF(E13<0.8,"cb_ أرخص بوضوح",IF(E13<=1.05,"تقارب","canboso أرخص"))) -> cb_ أرخص بوضوح
B14: 🛡️ Adguard VPN 7 Days full warranty | C14: 0.75 | D14: 1.49 | E14: =IFERROR(C14/D14,"") -> 0.5033557 | F14: =IF(E14="","",IF(E14<0.8,"cb_ أرخص بوضوح",IF(E14<=1.05,"تقارب","canboso أرخص"))) -> cb_ أرخص بوضوح
B15: 😶‍🌫️ ADMIN MS365 PREMIUM 1TB 5 SLOTS 1 YEAR full warranty | C15: 13.72 | D15: 12.53 | E15: =IFERROR(C15/D15,"") -> 1.0949721 | F15: =IF(E15="","",IF(E15<0.8,"cb_ أرخص بوضوح",IF(E15<=1.05,"تقارب","canboso أرخص"))) -> canboso أرخص
B16: 😎 Adobe All Apps 7 Days no warranty | C16: 2.21 | D16: 3.01 | E16: =IFERROR(C16/D16,"") -> 0.73421927 | F16: =IF(E16="","",IF(E16<0.8,"cb_ أرخص بوضوح",IF(E16<=1.05,"تقارب","canboso أرخص"))) -> cb_ أرخص بوضوح
... B115: ❤️ Zoom Pro 28 Days full warranty | C115: 2.21 | D115: 3.01 | E115: =IFERROR(C115/D115,"") -> 0.73421927 | F115: =IF(E115="","",IF(E115<0.8,"cb_ أرخص بوضوح",IF(E115<=1.05,"تقارب","canboso أرخص"))) -> cb_ أرخص بوضوح
B116: الوسيط | E116: 0.912
B118: وسيط النسبة 0.912 (p25 0.764 · p75 1.066) — cb_ أرخص إجمالًا → canboso ليس المنبع الظاهر · الاستثناء: خط Deepseek API (أرخص على canboso 1.6-1.7×)

Sheet بوابة_teamsoclo
B2: بوابة teamsoclo — تسعيرة النماذج (15 موديلًا · الإصدار a42d372c)
B4: الموديل | C4: نوع الحصة | D4: model_ratio | E4: model_price | F4: completion_ratio
B5: gpt-6-sol | C5: 0 | D5: 3 | E5: 0 | F5: 1
B6: gpt-6-astra | C6: 0 | D6: 30 | E6: 0 | F6: 1
B7: claude-opus-5 | C7: 0 | D7: 3 | E7: 0 | F7: 1
B8: gpt-5.6-sol | C8: 0 | D8: 3 | E8: 0 | F8: 1
B9: gpt-6.1-sol | C9: 0 | D9: 3 | E9: 0 | F9: 1
B10: gpt-astra | C10: 0 | D10: 37.5 | E10: 0 | F10: 2
B11: claude-fable-5 | C11: 0 | D11: 5 | E11: 0 | F11: 1
B12: claude-opus-4-6 | C12: 0 | D12: 2.5 | E12: 0 | F12: 5
B13: claude-opus-4-7 | C13: 0 | D13: 2.5 | E13: 0 | F13: 5
B14: claude-sonnet-5 | C14: 0 | D14: 37.5 | E14: 0 | F14: 1
B15: claude-opus-4-8 | C15: 0 | D15: 3 | E15: 0 | F15: 5
B16: claude-sonnet-4-6 | C16: 0 | D16: 37.5 | E16: 0 | F16: 5
... B19: gpt-6-luna | C19: 0 | D19: 2.5 | E19: 0 | F19: 1

Sheet المراجعة
B2: المراجعة — فحوص التطابق
B4: فحص | C4: المتوقع | D4: الفعلي | E4: الحالة
B5: منتجات StackVault الحي | C5: 282 | D5: =COUNTA(StackVault_الحي!B5:B286) -> 282 | E5: =IF(C5=D5,"✓ مطابق","✗ راجع") -> ✓ مطابق
B6: منتجات StackVault الأرشيف | C6: 357 | D6: =COUNTA(StackVault_الأرشيف!B5:B361) -> 357 | E6: =IF(C6=D6,"✓ مطابق","✗ راجع") -> ✓ مطابق
B7: سجلات الكيانات الخارجية | C7: 473 | D7: =COUNTA(الكيانات_الخارجية!B5:B477) -> 473 | E7: =IF(C7=D7,"✓ مطابق","✗ راجع") -> ✓ مطابق
B8: أزواج مقارنة الأسعار | C8: 111 | D8: =COUNTA(مقارنة_الأسعار!B5:B115) -> 111 | E8: =IF(C8=D8,"✓ مطابق","✗ راجع") -> ✓ مطابق
B9: موديلات البوابة | C9: 15 | D9: =COUNTA(بوابة_teamsoclo!B5:B19) -> 15 | E9: =IF(C9=D9,"✓ مطابق","✗ راجع") -> ✓ مطابق
B10: إجمالي سجلات المنتجات | C10: 1112 | D10: =D5+D6+D7 -> 1112 | E10: =IF(C10=D10,"✓ مطابق","✗ راجع") -> ✓ مطابق
